{
    "numMessagesInTopic": 5, 
    "nextInTime": 1411, 
    "senderId": "_cdfgDJyBVLLXVnDNL-aRYwV7EndbsQUTFLjgMiaxGaFPa3RTnkxP9Ke1P_2w8KZuw1KVGGrNyQBgyQHgIwzOshM_HSHEkE", 
    "systemMessage": false, 
    "subject": "RE: [junit] RPM available for junit", 
    "from": "John McAtee &lt;johnm@...&gt;", 
    "authorName": "John McAtee", 
    "msgSnippet": "RedHat Package Manager, very useful for those of us living in RedHat Linux! John. ... From: Yishay Mor [mailto:ymor@cisco.com] Sent: Thursday, June 07, 2001", 
    "msgId": 1410, 
    "topicId": 1405, 
    "spamInfo": {
        "reason": "0", 
        "isSpam": false
    }, 
    "replyTo": "LIST", 
    "userId": 0, 
    "messageBody": "<div id=\"ygrps-yiv-1187810353\">\n<html><head>\n \n\n\n</head> \n \n<div><font color=\"#0000ff\" face=\"Arial\" size=\"2\"><span class=\"ygrps-yiv-1187810353120232414-07062001\">RedHat \nPackage Manager, very useful for those of us living in RedHat \nLinux!</span></font></div>\n<div><font color=\"#0000ff\" face=\"Arial\" size=\"2\"><span\n class=\"ygrps-yiv-1187810353120232414-07062001\"></span></font>&nbsp;</div>\n<div><font color=\"#0000ff\" face=\"Arial\" size=\"2\"><span\n class=\"ygrps-yiv-1187810353120232414-07062001\">John.</span></font></div>\n<blockquote><span title=\"qreply\"> <blockquote>\n  <div align=\"left\" class=\"ygrps-yiv-1187810353OutlookMessageHeader\" dir=\"ltr\"><font face=\"Tahoma\"\n size=\"2\">-----Original Message-----<br><b>From:</b> Yishay Mor \n  [mailto:ymor@...]<br><b>Sent:</b> Thursday, June 07, 2001 7:02 \n  AM<br><b>To:</b> junit@yahoogroups.com<br><b>Subject:</b> Re: [junit] RPM \n  available for junit<br><br></font></div>What is RPM?<br><br>At 10:14 AM \n  6/7/2001 +0000, you wrote:<br>\n  <blockquote cite type=\"cite\">Hi to all,<br><br>A quick note to inform RPM \n    users, that <br>Junit 3.7 RPM are available at :<br><br><a rel=\"nofollow\"\n target=\"_blank\" href=\"ftp://ftp.falsehope.com/home/gomez/junit/\"\n>ftp://ftp.falsehope.com/home/gomez/junit/</a><br><br>Next \n    to RPMs for jakarta.apache.org and xml.apache.org <br>projects \n    :)<br><br>Regards.<br><br><br><br><br>To unsubscribe from this group, send \n    an email to:<br>junit-unsubscribe@yahoogroups.com<br>&nbsp;<br><br>Your use \n    of Yahoo! Groups is subject to <a rel=\"nofollow\" target=\"_blank\" href=\"http://docs.yahoo.com/info/terms/\"\n>http://docs.yahoo.com/info/terms/</a> </blockquote><br>\n  <hr>\n  &nbsp;&nbsp;&nbsp;&nbsp;&nbsp;&nbsp;&nbsp;&nbsp; Yishay \n  Mor<br> &nbsp;&nbsp;&nbsp;&nbsp;&nbsp;&nbsp;&nbsp;&nbsp; Cisco \n  systems, EMBU Israel&nbsp; (QPM \n  project)<br> &nbsp;&nbsp;&nbsp;&nbsp;&nbsp;&nbsp;&nbsp;&nbsp; work&nbsp; \n  +972-9-9700031 &nbsp;&nbsp;&nbsp;&nbsp; home +972-4-6396602 \n  <br> &nbsp;&nbsp;&nbsp;&nbsp;&nbsp;&nbsp;&nbsp;&nbsp; ymor@... \n  <br><br><tt>To \n  unsubscribe from this group, send an email \n  to:<br>junit-unsubscribe@yahoogroups.com<br></tt><br><br><tt>Your use of \n  Yahoo! Groups is subject to the <a rel=\"nofollow\"\n target=\"_blank\" href=\"http://docs.yahoo.com/info/terms/\">Yahoo! Terms of Service</a>.</tt> \n<br></blockquote></span></blockquote></html> \n</div>", 
    "prevInTime": 1409, 
    "specialLinks": [], 
    "contentTrasformed": false, 
    "postDate": "991924029", 
    "canDelete": false, 
    "nextInTopic": 0, 
    "prevInTopic": 1408, 
    "headers": {
        "messageIdInHeader": "PDUyNUQxRUU2NDczM0Q0MTFCMTBFMDA1MDA0RTE5QTRDMDEzQkYxQG1haWwuY29yZXNvZnQuY29tPg=="
    }
}