{
    "numMessagesInTopic": 1, 
    "nextInTime": 4259, 
    "senderId": "aSD_s64tgxXyrTYE6w2soDsnPv1-s629gxOoX1WhwKEzDgu0_DtTpblf1xq5rsnaR06knu_CguSoXZtYaYihxGiA95poUMgfBg", 
    "systemMessage": false, 
    "subject": "Jython with JUnit", 
    "from": "&quot;daviddench&quot; &lt;d.j.dench@...&gt;", 
    "authorName": "daviddench", 
    "msgSnippet": "Dear All, I am having a few niggling problems calling JUnit from Jython. Does anyone have a ported version of the samples/SimpleTest demos that I can borrow to", 
    "msgId": 4258, 
    "rawEmail": "Return-Path: &lt;d.j.dench@...&gt;\r\nX-Sender: d.j.dench@...\r\nX-Apparently-To: junit@yahoogroups.com\r\nReceived: (EGP: unknown); 4 Mar 2002 11:16:29 -0000\r\nReceived: (qmail 45902 invoked from network); 4 Mar 2002 11:16:29 -0000\r\nReceived: from unknown (216.115.97.167)\n  by m3.grp.snv.yahoo.com with QMQP; 4 Mar 2002 11:16:29 -0000\r\nReceived: from unknown (HELO n4.groups.yahoo.com) (216.115.96.54)\n  by mta1.grp.snv.yahoo.com with SMTP; 4 Mar 2002 11:16:29 -0000\r\nReceived: from [216.115.96.130] by n4.groups.yahoo.com with NNFMP; 04 Mar 2002 11:16:29 -0000\r\nDate: Mon, 04 Mar 2002 11:16:24 -0000\r\nTo: junit@yahoogroups.com\r\nSubject: Jython with JUnit \r\nMessage-ID: &lt;a5vl28+rrrh@...&gt;\r\nUser-Agent: eGroups-EW/0.82\r\nMIME-Version: 1.0\r\nContent-Type: text/plain; charset=ISO-8859-1\r\nContent-Length: 249\r\nX-Mailer: Yahoo Groups Message Poster\r\nFrom: &quot;daviddench&quot; &lt;d.j.dench@...&gt;\r\nX-Yahoo-Group-Post: member; u=23466213\r\nX-Yahoo-Profile: daviddench\r\n\r\nDear All,\nI am having a few niggling problems calling JUnit from Jython.\nDoes anyone have a ported version of the samples/SimpleTest demos\nthat I can borrow to get me sorted ? It&#39;s the auto suite generation\nthat is causing problems.\nThanks,\n\tDavid\n\n\n\n", 
    "profile": "daviddench", 
    "topicId": 4258, 
    "spamInfo": {
        "reason": "0", 
        "isSpam": false
    }, 
    "replyTo": "LIST", 
    "userId": 23466213, 
    "prevInTime": 4257, 
    "contentTrasformed": false, 
    "postDate": "1015240584", 
    "canDelete": false, 
    "nextInTopic": 0, 
    "prevInTopic": 0, 
    "headers": {
        "messageIdInHeader": "PGE1dmwyOCtycnJoQGVHcm91cHMuY29tPg=="
    }
}