{
    "topicId": 4941, 
    "postDate": "1021177750", 
    "spamInfo": {
        "reason": "0", 
        "isSpam": false
    }, 
    "from": "&quot;Alexander Zynevich&quot; &lt;java@...&gt;", 
    "canDelete": false, 
    "replyTo": "LIST", 
    "senderId": "_aI5aJoSAoX6BdVTVPw8a8QHDggGjdWTcl1_kNOycZsTHTafB5pmlruQ24v9eA8NDoQdAWPmU7fJ61R_hkmq19SR9ktX9Cg7Hg", 
    "nextInTime": 4951, 
    "userId": 106886324, 
    "prevInTime": 4949, 
    "prevInTopic": 4949, 
    "headers": {
        "messageIdInHeader": "PDAwMWIwMWMxZjk2ZCQ5NWNmODA0MCRhMmQwOWVjMkB6eW5ldmljaD4=", 
        "referencesHeader": "PEUxNzZmcXItMDAwNDk5LTAwQG1ydmRvbTAxLmt1bmRlbnNlcnZlci5kZT4="
    }, 
    "authorName": "Alexander Zynevich", 
    "numMessagesInTopic": 11, 
    "msgSnippet": "As well it will test forNaN correctly... ... From: Lothar Kimmeringer  To:  Sent: Sunday, May 12, 2002 2:03 AM ", 
    "contentTrasformed": false, 
    "msgId": 4950, 
    "nextInTopic": 4952, 
    "systemMessage": false, 
    "rawEmail": "Return-Path: &lt;java@...&gt;\r\nX-Sender: java@...\r\nX-Apparently-To: junit@yahoogroups.com\r\nReceived: (EGP: mail-8_0_3_2); 12 May 2002 04:29:41 -0000\r\nReceived: (qmail 59656 invoked from network); 12 May 2002 04:29:40 -0000\r\nReceived: from unknown (66.218.66.217)\n  by m9.grp.scd.yahoo.com with QMQP; 12 May 2002 04:29:40 -0000\r\nReceived: from unknown (HELO tut.by) (217.106.234.113)\n  by mta2.grp.scd.yahoo.com with SMTP; 12 May 2002 04:29:39 -0000\r\nReceived: from [194.158.208.162] (account java HELO zynevich)\n  by tut.by (CommuniGate Pro SMTP 3.5.6)\n  with ESMTP id 13768430 for junit@yahoogroups.com; Sun, 12 May 2002 07:29:36 +0300\r\nMessage-ID: &lt;001b01c1f96d$95cf8040$a2d09ec2@zynevich&gt;\r\nTo: &lt;junit@yahoogroups.com&gt;\r\nReferences: &lt;E176fqr-000499-00@...&gt;\r\nSubject: Re: [junit] No assertEquals(double, double)?\r\nDate: Sun, 12 May 2002 07:29:10 +0300\r\nMIME-Version: 1.0\r\nContent-Type: text/plain;\n\tcharset=&quot;iso-8859-1&quot;\r\nContent-Transfer-Encoding: 7bit\r\nX-Priority: 3\r\nX-MSMail-Priority: Normal\r\nX-Mailer: Microsoft Outlook Express 6.00.2600.0000\r\nX-MimeOLE: Produced By Microsoft MimeOLE V6.00.2600.0000\r\nFrom: &quot;Alexander Zynevich&quot; &lt;java@...&gt;\r\nReply-To: &quot;Alexander Zynevich&quot; &lt;java@...&gt;\r\nX-Yahoo-Group-Post: member; u=106886324\r\n\r\nAs well it will test forNaN correctly...\n----- Original Message -----\nFrom: &quot;Lothar Kimmeringer&quot; &lt;junit@...&gt;\nTo: &lt;junit@yahoogroups.com&gt;\nSent: Sunday, May 12, 2002 2:03 AM\nSubject: Re: [junit] No assertEquals(double, double)?\n\n\n&gt; On Sun, 12 May 2002 01:17:47 +0300, Alexander Zynevich wrote:\n&gt;\n&gt; &gt;for example max(-0.0,+0.0) should return +0.0 if I test my own realizaton\nof\n&gt; &gt;max I will want to distinguish them :)\n&gt;\n&gt; I haven&#39;t tested it right now, but shouldn&#39;t\n&gt;\n&gt; assertEquals(&quot;check -0 and +0&quot;, new Double(-0d), new Double(0d));\n&gt;\n&gt; do the trick?\n&gt;\n&gt;\n&gt; Regards, Lothar\n&gt;\n&gt; --\n&gt; Lothar Kimmeringer                  E-Mail: lothar@...\n&gt;                PGP-encrypted mails preferred (Key-ID: 0x8BC3CD81)\n&gt;\n&gt; Always remember: The answer is forty-two, there can only be wrong\n&gt;                  questions!\n&gt;\n&gt;\n&gt;\n&gt;\n&gt; To unsubscribe from this group, send an email to:\n&gt; junit-unsubscribe@yahoogroups.com\n&gt;\n&gt;\n&gt; Your use of Yahoo! Groups is subject to http://docs.yahoo.com/info/terms/\n&gt;\n&gt;\n\n\n", 
    "subject": "Re: [junit] No assertEquals(double, double)?"
}