{
    "topicId": 6070, 
    "postDate": "1036080070", 
    "spamInfo": {
        "reason": "0", 
        "isSpam": false
    }, 
    "from": "&quot;Durham David Cntr 805CSS/SCBE&quot; &lt;David.Durham1@...&gt;", 
    "canDelete": false, 
    "replyTo": "LIST", 
    "senderId": "5mFN3z9nqrfDN-uaVNOvrimeIHqWsjQHv6hIEe3P6x9GvhqKTx9Tlb06KQT98s-8SVI48wfctwKNcpzrVKX3ivgE-2y8sU3E8RVFw_gTWCi07p2xapUG25RHEc6cINsCCnZg", 
    "nextInTime": 6071, 
    "userId": 122988120, 
    "prevInTime": 6069, 
    "prevInTopic": 0, 
    "headers": {
        "messageIdInHeader": "PEUzQzdCNDA1ODA5NTIwNDk5MDZCRUIxNzk3MzU5OUIyMEZEQzhBQGFtY3cybXM4MTQuYW1jLmRzLmFmLm1pbD4="
    }, 
    "authorName": "Durham David Cntr 805CSS/SCBE", 
    "numMessagesInTopic": 1, 
    "msgSnippet": "maybe it was the unwanted advertising at the bottom", 
    "contentTrasformed": false, 
    "msgId": 6070, 
    "nextInTopic": 0, 
    "systemMessage": false, 
    "rawEmail": "Return-Path: &lt;David.Durham1@...&gt;\r\nReceived: (qmail 28554 invoked from network); 31 Oct 2002 16:03:30 -0000\r\nReceived: from unknown (66.218.66.218)\n  by m12.grp.scd.yahoo.com with QMQP; 31 Oct 2002 16:03:30 -0000\r\nReceived: from unknown (HELO n22.grp.scd.yahoo.com) (66.218.66.78)\n  by mta3.grp.scd.yahoo.com with SMTP; 31 Oct 2002 16:03:30 -0000\r\nX-eGroups-Return: David.Durham1@...\r\nReceived: from [66.218.67.172] by n22.grp.scd.yahoo.com with NNFMP; 31 Oct 2002 16:03:30 -0000\r\nX-Sender: David.Durham1@...\r\nX-Apparently-To: junit@yahoogroups.com\r\nReceived: (EGP: mail-8_2_2_1); 31 Oct 2002 16:02:27 -0000\r\nReceived: (qmail 44711 invoked from network); 31 Oct 2002 16:02:27 -0000\r\nReceived: from unknown (66.218.66.217)\n  by m7.grp.scd.yahoo.com with QMQP; 31 Oct 2002 16:02:27 -0000\r\nReceived: from unknown (HELO fw1.amc.af.mil) (131.9.254.189)\n  by mta2.grp.scd.yahoo.com with SMTP; 31 Oct 2002 16:02:27 -0000\r\nReceived: from fw1.amc.af.mil (root@localhost)\n\tby fw1.amc.af.mil with ESMTP id g9VG2Qr14369\n\tfor &lt;junit@yahoogroups.com&gt;; Thu, 31 Oct 2002 10:02:26 -0600 (CST)\r\nReceived: from amcw2av802.amc.ds.af.mil (amcw2mr802.amc.af.mil [131.9.19.108])\n\tby fw1.amc.af.mil with SMTP id g9VG2Qf14364\n\tfor &lt;junit@yahoogroups.com&gt;; Thu, 31 Oct 2002 10:02:26 -0600 (CST)\r\nReceived: from amcw2ms875.amc.ds.af.mil ([131.9.25.137])\n by amcw2av802.amc.ds.af.mil (NAVGW 2.5.2.12) with SMTP id M2002103110022612660\n for &lt;junit@yahoogroups.com&gt;; Thu, 31 Oct 2002 10:02:26 -0600\r\nReceived: from amcw2ms814.amc.ds.af.mil ([131.9.19.81]) by amcw2ms875.amc.ds.af.mil with Microsoft SMTPSVC(5.0.2195.5329);\n\t Thu, 31 Oct 2002 10:02:22 -0600\r\nX-MimeOLE: Produced By Microsoft Exchange V6.0.6334.0\r\ncontent-class: urn:content-classes:message\r\nMIME-Version: 1.0\r\nContent-Type: text/plain;\n\tcharset=&quot;iso-8859-1&quot;\r\nContent-Transfer-Encoding: quoted-printable\r\nSubject: RE: [Fwd: Message Notification:  re: [junit] is there anassertbean(..)?]\r\nDate: Thu, 31 Oct 2002 10:01:10 -0600\r\nMessage-ID: &lt;E3C7B40580952049906BEB17973599B20FDC8A@...&gt;\r\nX-MS-Has-Attach: \r\nX-MS-TNEF-Correlator: \r\nThread-Topic: [Fwd: Message Notification:  re: [junit] is there anassertbean(..)?]\r\nThread-Index: AcKAwIRU8B3emGBqSGiTD/wIMgWVZAANi1vA\r\nTo: &lt;junit@yahoogroups.com&gt;\r\nX-OriginalArrivalTime: 31 Oct 2002 16:02:22.0054 (UTC) FILETIME=[E580F860:01C280F6]\r\nFrom: &quot;Durham David Cntr 805CSS/SCBE&quot; &lt;David.Durham1@...&gt;\r\nX-Yahoo-Group-Post: member; u=122988120\r\nX-eGroups-Approved-By: clarkware &lt;mike@...&gt; via web; 31 Oct 2002 16:03:26 -0000\r\n\r\nmaybe it was the unwanted advertising at the bottom\n\n&gt; -----Original Messag=\r\ne-----\n&gt; From: Robert Watkins [mailto:robertdw@...]\n&gt; Sent: Thur=\r\nsday, October 31, 2002 3:34 AM\n&gt; To: junit@yahoogroups.com\n&gt; Subject: [Fwd:=\r\n Message Notification: re: [junit] is there\n&gt; anassertbean(..)?]\n&gt; \n&gt; \n&gt; &gt; =\r\nFrom: Nemx Power Tools for MS Exchange Server_SFNTES_0 \n&gt; &lt;NMXEXSPP0_SFNTES=\r\n@...&gt;\n&gt; &gt; To: &#39;Robert Watkins&#39; &lt;robertdw@...&gt;\n&gt; &gt; Subject=\r\n: Message Notification:  re: [junit] is there an \n&gt; assertbean(..)?\n&gt; &gt; Dat=\r\ne: 31 Oct 2002 04:24:27 -0500\n&gt; &gt; \n&gt; &gt; The email message sent from Robert W=\r\natkins\n&gt; &gt; to junit@yahoogroups.com\n&gt; &gt; with the subject - re: [junit] is t=\r\nhere an assertbean(..)?\n&gt; &gt; had either objectionable words or phrases locat=\r\ned in - \n&gt; &gt; It was scanned by NEMX for Exchange Server and rejected.\n&gt; &gt; Y=\r\nou might try re-sending the email without offensive \n&gt; language or unwanted=\r\n\n&gt; &gt; advertising.\n&gt; \n&gt; Anyone have any idea what the offensive language cou=\r\nld have been? The\n&gt; &#39;ass&#39; in assert, perhaps?\n&gt; \n&gt; D*mn, it&#39;s not like I sa=\r\nid &#39;f2k&#39; or &#39;s2t&#39;, is it?  &*#@ to them! :)\n&gt; \n&gt; Robert.\n&gt; \n&gt; -- \n&gt;        =\r\n        &quot;Software is too expensive to build cheaply&quot;\n&gt;   Robert Watkins    =\r\n                      email: \n&gt; robertdw@...\n&gt; \n&gt; \n&gt; -----------=\r\n------------- Yahoo! Groups Sponsor \n&gt; ---------------------~--&gt;\n&gt; Get 128 =\r\nBit SSL Encryption!\n&gt; http://us.click.yahoo.com/JjlUgA/vN2EAA/kG8FAA/5cFolB=\r\n/TM\n&gt; --------------------------------------------------------------\n&gt; ----=\r\n---~-&gt;\n&gt; \n&gt; To unsubscribe from this group, send an email to:\n&gt; junit-unsub=\r\nscribe@yahoogroups.com\n&gt;  \n&gt; \n&gt; Your use of Yahoo! Groups is subject to \n&gt; =\r\nhttp://docs.yahoo.com/info/terms/ \n&gt; \n&gt; \n&gt; \n\n\n", 
    "subject": "RE: [Fwd: Message Notification:  re: [junit] is there anassertbean(..)?]"
}